gdget/GdGet.py
gdget/__init__.py
gdget/__main__.py
gdget/cli.py
gdget-0.1.1.dist-info/DESCRIPTION.rst
gdget-0.1.1.dist-info/METADATA
gdget-0.1.1.dist-info/RECORD
gdget-0.1.1.dist-info/WHEEL
gdget-0.1.1.dist-info/entry_points.txt
gdget-0.1.1.dist-info/metadata.json
gdget-0.1.1.dist-info/top_level.txt
