Metadata-Version: 2.0
Name: gdget
Version: 0.1.1
Summary: Google drive URLs downloader for command line.
Home-page: https://github.com/v1shwa/gdget
Author: Vishwa
Author-email: v1shwa@yahoo.com
License: MIT
Keywords: googledrive cli google download
Platform: UNKNOWN
Classifier: Intended Audience :: Developers
Classifier: Topic :: Utilities
Classifier: License :: OSI Approved :: MIT License
Classifier: Natural Language :: English
Classifier: Operating System :: OS Independent
Classifier: Programming Language :: Python :: 2
Classifier: Programming Language :: Python :: 2.6
Classifier: Programming Language :: Python :: 2.7
Classifier: Programming Language :: Python :: 3
Classifier: Programming Language :: Python :: 3.2
Classifier: Programming Language :: Python :: 3.4
Classifier: Programming Language :: Python :: 3.5
Classifier: Programming Language :: Python :: 3.6
Classifier: Programming Language :: Python :: 3.7
Requires-Python: >=2.6, !=3.0.*, !=3.1.*, !=3.2.*, !=3.3.*, <4
Requires-Dist: requests
Requires-Dist: tqdm
Provides-Extra: test
Requires-Dist: pytest; extra == 'test'
